butler2fox/__init__.py
butler2fox/color.py
butler2fox/gitlab/model.py
butler2fox/jenkins/__init__.py
butler2fox/jenkins/ast.py
butler2fox/jenkins/model.py
butler2fox/migrator/__init__.py
butler2fox/migrator/steps.py
butler2fox/stats.py
butler2fox-1.0.0.dist-info/LICENSE.txt
butler2fox-1.0.0.dist-info/METADATA
butler2fox-1.0.0.dist-info/WHEEL
butler2fox-1.0.0.dist-info/entry_points.txt
butler2fox-1.0.0.dist-info/RECORD
