Metadata-Version: 2.3
Name: butler2fox
Version: 1.0.0
Summary: Migrate your CI/CD pipelines from Jenkins to GitLab.
License: MIT
Keywords: tool,migration,Jenkins,GitLab
Author: Pierre Smeyers
Author-email: pierre.smeyers@gmail.com
Requires-Python: >=3.12
Classifier: Development Status :: 4 - Beta
Classifier: Environment :: Console
Classifier: Intended Audience :: Developers
Classifier: License :: OSI Approved :: MIT License
Classifier: Operating System :: OS Independent
Classifier: Programming Language :: Python
Classifier: Programming Language :: Python :: 3
Classifier: Programming Language :: Python :: 3.12
Classifier: Programming Language :: Python :: 3.13
Classifier: Programming Language :: Python :: 3.14
Classifier: Programming Language :: Python :: 3 :: Only
Requires-Dist: arpeggio (>=2.0.2,<3.0.0)
Requires-Dist: pyyaml (>=6.0.2,<7.0.0)
Project-URL: Homepage, https://gitlab.com/pismy/butler2fox
Project-URL: Issues, https://gitlab.com/pismy/butler2fox/-/issues
